django_searchable/__init__.py
django_searchable/exceptions.py
django_searchable/models.py
django_searchable-0.1.2.dist-info/METADATA
django_searchable-0.1.2.dist-info/RECORD
django_searchable-0.1.2.dist-info/WHEEL
django_searchable-0.1.2.dist-info/top_level.txt
tests/__init__.py
tests/models.py
tests/settings.py
tests/test_django_search.py
