Metadata-Version: 2.1
Name: django-searchable
Version: 0.1.2
Summary: Easy FTS with Django and PostgreSQL
Home-page: https://github.com/rjauquet/django-searchable
Author: Rob Ervin Jauquet
Author-email: rjauquet@gmail.com
License: UNKNOWN
Download-URL: https://github.com/rjauquet/django-searchable/archive/0.1.2.tar.gz
Keywords: search,searchable,fts
Platform: UNKNOWN
Requires-Dist: Django (>=2.x)
Requires-Dist: psycopg2-binary (>=2.7.4)
